<?xml version="1.0" encoding="utf-8" ?>
<creature>
  <!--
    info - 관찰 레벨과는 관련 없는 정보들 ex)데미지, id, 이미지 소스 등
    
    observe - 관찰 정도에 따라 제공되는 정보들
              각 정보들에는 정보가 제공되는 레벨을 표기
              ex) <desc id="1" openLevel="1">"openLevel이 1일 때 이 정보가 제공됨"</desc>
              
              observe 노드 안의 level 은 관찰 단계의 갯수를 나타냄
  -->
  <info id ="110012">



    <narration action="move">
      #0 заходит в камеру содержания Аномалии $0.
    </narration>

    <narration action="mid1">
      [
      {Сотрудник #0 чувствует, что их тела лишены энергии.}
      ]
    </narration>
    <narration action="mid2">
      [
      {Беды Аномалии $0 непостижимо глубоки.},
      {Аномалия $0 хочет быть освобождена от её горя.},

      ]
    </narration>
    <narration action="mid3">
      [
      {Сотрудник #0 чувствует боль, словно ему раздавили голову и грудь.}
      ]
    </narration>

  </info>

  <observe level ="1">
    <collection>
      <codeNo openLevel ="0">F-05-33</codeNo>
      <portrait openLevel ="1">Custom/DrownedSister</portrait>

      <name openLevel ="1">
       Утопленные сёстры
      </name>

      <riskLevel openLevel ="1">
        HE
      </riskLevel>

      <specialName openLevel ="1">
       Sorrow
      </specialName>
      <openText>"За что ты нас так презирал?"</openText>
    
    </collection>

    <desc id="1" openLevel="0">
      [
      {Почему ты так презирал нас? Откуда в тебе столько ненависти, что желал нашей смерти?}
      ]
    </desc>

    <desc id="2" openLevel="1">
      [
      {Сказал бы ты хоть слово, хоть слово о том, как ты нас ненавидел...}
      ]
    </desc>

    <desc id="3" openLevel="2">
      [
      {Ахх, горе нам. Мы стали грешниками. Просим, услышать нас, услышь наши грехи, мы не знаем, что совершили...}
      ]
    </desc>

    <desc id="4" openLevel="3">
      [
      {И освободи от нашей печали...}
      ]
    </desc>


    
  <specialTipSize size="5">
      <specialTip openLevel="0" key="nope">После завершения работы с другой Аномалией, а не с Аномалией $0, уровень счётчика Клипот понижается.</specialTip>
      <specialTip openLevel="0" key="nope">В результате Хорошей работы на Инстинкт, уровень счётчика Клипот повысится.</specialTip>
      <specialTip openLevel="0" key="nope">После завершения работы на Подавление уровень счётчика Клипота понизился до 0.</specialTip>
      <specialTip openLevel="0" key="nope">Когда счётчик Клипота достигнет 0, то коридор, в котором находится Аномалия будет залит водой. Сотрудники, проходившие через этот коридор получали огромное количество БЕЛОГО урона.</specialTip>
      <specialTip openLevel="0" key="nope">Счётчик Клипота Аномалии $0 можно полностью восстановить, выполнив особую работу, 'работу на Освобождение'. Однако, слушая о несчастьях Аномалии $0, Мудрость Агента будет уменьшена вдвое до конца дня.</specialTip>
     </specialTipSize>
    
   <max>
      <!--기본 선택지-->
      <desc id="0" select="1">
        [
        {Сцена была установлена давным-давно, и вот появится человек, убивший много людей.}
        {По случайному сопадению у вас под рукой пистолет.}
        <!--계속-->
        ]
      </desc>

      <!--선택지-->
      <select id="1">
        <node desc="Застрелить его." target="1" isAnswer="true"  message="Занавес открывается." />
        <node desc="Наблюдать." target="2" isAnswer="true" message="Занавес открывается." />
        <node desc="Выстрелить в кого-нибудь." target="3" isAnswer="true" message="Занавес открывается." />
      </select>

      <desc id="1" select="0">
        [
        {Вы решаетесь застрелить человека.}
        {Наконец, занавес опускается.}
        ]
      </desc>

      <desc id="2" select="0">
        [
        {Ствол пистолета потерял свою цель.}
        {Сцена закончилась трагедией.}
        ]
      </desc>

      <desc id="3" select="0">
        [
        {Сцена заканчивается комедией.}
        ]
      </desc>

      <!--스토리 파트에서 출력될 부분-->
      <angela>
        [
        {"Грешник, наблюдающий за пьесой, движимый своими эксцентричными способами выражения вещей, сразу же исповедует свои грехи. Пьеса обязательно раскроет свой истинный посыл."}
        ]
      </angela>
    </max>
    
  </observe>

  <etc>
    <param key="attack1" index="0"> <!-- 더미데이터였던...카핰 -->
      A : (Рассказывает) Он был всего лишь эгоцентричным и высокомерным человеком. (Поглаживая маску) Я знал это с самого начала. Ведь катастрофа следует за катастрофой.
    </param>
    <param key="attack2" index="1">
      A : (Рассказывает) Та, что покинула этот мир, я буду служить тебе до смерти, ибо я достоин этого. Жажда, которую мне ещё предстоит утолить, приближается.
    </param>
    <param key="attack3" index="2">
      A : (Рассказывает) Его отчаяние уже просочилось глубоко в его кости, разъедая изнутри. Хоть он всегда улыбался, но глубоко в душе он себя ненавидел.
    </param>
    <param key="attack4" index="3">
      A : (Рассказывает) Он всего лишь трус, который избегает своих неудач. Я не могу его простить. Ведь я лишь тот, кто вместе с тобой бродит по раю или аду!
    </param>

    <param key="kill1" index="4"> <!-- 각각 죽이고 나서 대사 으안안ㅁ아앜앜어안ㄴ앜 -->
      (Тот, кто потерпел неудачу - падает.)
    </param>
    <param key="kill2" index="5">
      (Тот, кого бросили - падает.)
    </param>
    <param key="kill3" index="6">
      (Тот, кто отчаялся - падает.)
    </param>
    <param key="kill4" index="7">
      (Тот, кто избегал всего - падает.)
    </param>


    <param key="finale1" index="8"> <!-- 쥔공한테 총 쏠때-->
     A :  Умереть - это всего лишь погрузиться в сон, и ничего больше. (Падает)
    </param>

    <param key="finale2" index="9"><!--총 안쏠때-->
      A : Были ли выявлены грехи в моём диалоге? (Гаснет свет)
    </param>

    <param key="finale3" index="10"> <!-- 다른 사람한테 쏠때-->
      A :  Господи боже, нет. Прошу, помоги мне. Избавь меня от этой боли. (Сокрушительная тишина)
    </param>
    
    

    <param key="special" index="11"> <!-- 특수공격 발동 되기 시작할때-->
      Вы теперь не можете контролировать Агента #0. Всё его внимание сосредоточено на этой книге. Начинается спектакль.
    </param>


    <param key="end" index="12"> <!-- 연출없이 끝날때-->
      Ты, потерянный во тьме и окружённый тишиной. Пусть раньше и начинался рассвет, но сейчас же это всего лишь вечная ночь. Если бы я мог дотянуться до тебя, я бы вывел тебя из этой отвратительной тьмы в сияющий свет.
    </param>




  </etc>
  

</creature>